pyautodep
