Metadata-Version: 2.1
Name: pyautodep
Version: 0.0.2
Summary: Check and install python modules
Home-page: UNKNOWN
Author: Yoel Mountanus Sitorus
Author-email: sclous2012@gmail.com
License: UNKNOWN
Keywords: python,package,autoinstall,pypi package
Platform: UNKNOWN
Classifier: Development Status :: 1 - Planning
Classifier: Intended Audience :: Developers
Classifier: Programming Language :: Python :: 3
Classifier: Operating System :: Unix
Classifier: Operating System :: MacOS :: MacOS X
Classifier: Operating System :: Microsoft :: Windows
